Yogesh_Nile/__init__.py
Yogesh_Nile-0.1.0.dist-info/LICENSE
Yogesh_Nile-0.1.0.dist-info/METADATA
Yogesh_Nile-0.1.0.dist-info/WHEEL
Yogesh_Nile-0.1.0.dist-info/top_level.txt
Yogesh_Nile-0.1.0.dist-info/RECORD
