Metadata-Version: 2.1
Name: Yogesh-Nile
Version: 0.1.0
Summary: Yogesh Nile's Library
Home-page: https://github.com/yogeshnile/yogesh-nile-pypi
Author: Yogesh Nile
Author-email: yogeshnile.work4u@gmail.com
License: MIT
Platform: UNKNOWN
Classifier: Programming Language :: Python :: 3
Classifier: License :: OSI Approved :: MIT License
Classifier: Operating System :: OS Independent
Requires-Python: >=3.6
